<PAMDataset>
  <PAMRasterBand band="1">
    <Metadata>
      <MDI key="STATISTICS_MAXIMUM">223</MDI>
      <MDI key="STATISTICS_MEAN">143.07465277778</MDI>
      <MDI key="STATISTICS_MINIMUM">38</MDI>
      <MDI key="STATISTICS_STDDEV">35.938696596759</MDI>
      <MDI key="STATISTICS_VALID_PERCENT">100</MDI>
    </Metadata>
  </PAMRasterBand>
  <PAMRasterBand band="2">
    <Metadata>
      <MDI key="STATISTICS_MAXIMUM">197</MDI>
      <MDI key="STATISTICS_MEAN">137.14930555556</MDI>
      <MDI key="STATISTICS_MINIMUM">50</MDI>
      <MDI key="STATISTICS_STDDEV">36.531644381062</MDI>
      <MDI key="STATISTICS_VALID_PERCENT">100</MDI>
    </Metadata>
  </PAMRasterBand>
  <PAMRasterBand band="3">
    <Metadata>
      <MDI key="STATISTICS_MAXIMUM">201</MDI>
      <MDI key="STATISTICS_MEAN">132.46527777778</MDI>
      <MDI key="STATISTICS_MINIMUM">55</MDI>
      <MDI key="STATISTICS_STDDEV">38.14663105746</MDI>
      <MDI key="STATISTICS_VALID_PERCENT">100</MDI>
    </Metadata>
  </PAMRasterBand>
</PAMDataset>
